syac/__init__.py
syac-0.1.dist-info/LICENSE.txt
syac-0.1.dist-info/METADATA
syac-0.1.dist-info/WHEEL
syac-0.1.dist-info/top_level.txt
syac-0.1.dist-info/RECORD
