Metadata-Version: 2.1
Name: syac
Version: 0.1
Summary: Packages and Dependencies
Home-page: UNKNOWN
Author: kitsune
Author-email: bluefang@gmail.com
License: UNKNOWN
Platform: UNKNOWN
Classifier: Programming Language :: Python :: 3
Classifier: License :: OSI Approved :: MIT License
Classifier: Operating System :: OS Independent
License-File: LICENSE.txt
